django_export_excel/__init__.py
django_export_excel/admin.py
django_export_excel/colors.py
django_export_excel/exceptions.py
django_export_excel/exporter.py
django_export_excel/styles.py
django_export_excel/table.py
django_export_excel/views.py
django_export_excel-1.0.6.dist-info/LICENCE
django_export_excel-1.0.6.dist-info/METADATA
django_export_excel-1.0.6.dist-info/WHEEL
django_export_excel-1.0.6.dist-info/top_level.txt
django_export_excel-1.0.6.dist-info/RECORD
